{
  "resourceType": "Observation",
  "id": "FSC-SNF-DischargeGoal-Mobility-SelfCare-1",
  "meta": {
    "profile": [
      "http://paciowg.github.io/functional-status-ig/StructureDefinition/pacio-fsc"
    ]
  },
  "text": {
    "status": "extensions",
    "div": "<div xmlns=\"http://www.w3.org/1999/xhtml\"><p><b>Generated Narrative</b></p><p><b>ObservationEventLocation</b>: <a href=\"Location-Org-Loc-02.html\">Generated Summary: status: active; name: Happy Nursing Facility</a></p><p></p><p><b>category</b>: <span title=\"Codes: {http://paciowg.github.io/cognitive-status-ig/CodeSystem/pacio-cat-cs functioning}\">Functioning</span>, <span title=\"Codes: {http://terminology.hl7.org/CodeSystem/observation-category survey}\">Survey</span></p><p><b>code</b>: <span title=\"Codes: {http://loinc.org 85054-5}\">Self-care - discharge goal [CMS Assessment]</span></p><p><b>subject</b>: <a href=\"Patient-patientBSJ1.html\">Generated Summary: Betsy Smith-Johnson </a></p><p><b>effective</b>: Jul 11, 2020, 2:32:00 PM</p><p><b>performer</b>: <a href=\"PractitionerRole-Role-OT-JenCadbury.html\">Generated Summary: active; <span title=\"Codes: {http://snomed.info/sct 80546007}\">Occupational therapist</span></a></p><p><b>hasMember</b>: </p><ul><li><a href=\"Observation-FSC-SNF-DischargeGoal-Mobility-SelfCare-1-Ob-Question-29.html\">Generated Summary: <span title=\"Codes: {http://paciowg.github.io/cognitive-status-ig/CodeSystem/pacio-cat-cs functioning}\">Functioning</span>, <span title=\"Codes: {http://terminology.hl7.org/CodeSystem/observation-category survey}\">Survey</span>; <span title=\"Codes: {http://loinc.org 83231-1}\">Eating</span>; effective: Jul 11, 2020, 2:32:00 PM; <span title=\"Codes: {http://loinc.org LA9983-3}\">Independent</span></a></li><li><a href=\"Observation-FSC-SNF-DischargeGoal-Mobility-SelfCare-1-Ob-Question-30.html\">Generated Summary: <span title=\"Codes: {http://paciowg.github.io/cognitive-status-ig/CodeSystem/pacio-cat-cs functioning}\">Functioning</span>, <span title=\"Codes: {http://terminology.hl7.org/CodeSystem/observation-category survey}\">Survey</span>; <span title=\"Codes: {http://loinc.org 83229-5}\">Oral hygiene</span>; effective: Jul 11, 2020, 2:32:00 PM; <span title=\"Codes: {http://loinc.org LA9983-3}\">Independent</span></a></li><li><a href=\"Observation-FSC-SNF-DischargeGoal-Mobility-SelfCare-1-Ob-Question-31.html\">Generated Summary: <span title=\"Codes: {http://paciowg.github.io/cognitive-status-ig/CodeSystem/pacio-cat-cs functioning}\">Functioning</span>, <span title=\"Codes: {http://terminology.hl7.org/CodeSystem/observation-category survey}\">Survey</span>; <span title=\"Codes: {http://loinc.org 83227-9}\">Toileting hygiene</span>; effective: Jul 11, 2020, 2:32:00 PM; <span title=\"Codes: {http://loinc.org LA11757-4}\">Supervision or touching assistance</span></a></li><li><a href=\"Observation-FSC-SNF-DischargeGoal-Mobility-SelfCare-1-Ob-Question-32.html\">Generated Summary: <span title=\"Codes: {http://paciowg.github.io/cognitive-status-ig/CodeSystem/pacio-cat-cs functioning}\">Functioning</span>, <span title=\"Codes: {http://terminology.hl7.org/CodeSystem/observation-category survey}\">Survey</span>; <span title=\"Codes: {http://loinc.org 83225-3}\">Shower/bathe self</span>; effective: Jul 11, 2020, 2:32:00 PM; <span title=\"Codes: {http://loinc.org LA11759-0}\">Substantial/maximal assistance</span></a></li><li><a href=\"Observation-FSC-SNF-DischargeGoal-Mobility-SelfCare-1-Ob-Question-33.html\">Generated Summary: <span title=\"Codes: {http://paciowg.github.io/cognitive-status-ig/CodeSystem/pacio-cat-cs functioning}\">Functioning</span>, <span title=\"Codes: {http://terminology.hl7.org/CodeSystem/observation-category survey}\">Survey</span>; <span title=\"Codes: {http://loinc.org 83223-8}\">Upper body dressing</span>; effective: Jul 11, 2020, 2:32:00 PM; <span title=\"Codes: {http://loinc.org LA10073-7}\">Setup or cleanup assistance</span></a></li><li><a href=\"Observation-FSC-SNF-DischargeGoal-Mobility-SelfCare-1-Ob-Question-34.html\">Generated Summary: <span title=\"Codes: {http://paciowg.github.io/cognitive-status-ig/CodeSystem/pacio-cat-cs functioning}\">Functioning</span>, <span title=\"Codes: {http://terminology.hl7.org/CodeSystem/observation-category survey}\">Survey</span>; <span title=\"Codes: {http://loinc.org 83221-2}\">Lower body dressing</span>; effective: Jul 11, 2020, 2:32:00 PM; <span title=\"Codes: {http://loinc.org LA10055-4}\">Partial/moderate assistance</span></a></li><li><a href=\"Observation-FSC-SNF-DischargeGoal-Mobility-SelfCare-1-Ob-Question-35.html\">Generated Summary: <span title=\"Codes: {http://paciowg.github.io/cognitive-status-ig/CodeSystem/pacio-cat-cs functioning}\">Functioning</span>, <span title=\"Codes: {http://terminology.hl7.org/CodeSystem/observation-category survey}\">Survey</span>; <span title=\"Codes: {http://loinc.org 83219-6}\">Putting on/taking off footwear</span>; effective: Jul 11, 2020, 2:32:00 PM; <span title=\"Codes: {http://loinc.org LA10055-4}\">Partial/moderate assistance</span></a></li></ul><p><b>derivedFrom</b>: <a href=\"QuestionnaireResponse-QResponse-SNF-DischargeGoal-Mobility-SelfCare-1.html\">Questionnaire Response. Generated Summary: questionnaire: https://api.logicahealth.org/PACIO/open/Questionnaire/MDS3.0-NC-1.17; status: completed; authored: Jul 11, 2020, 2:32:00 PM</a></p></div>"
  },
  "extension": [
    {
      "url": "http://paciowg.github.io/functional-status-ig/StructureDefinition/event-location",
      "valueReference": {
        "reference": "Location/Org-Loc-02"
      }
    }
  ],
  "status": "final",
  "category": [
    {
      "coding": [
        {
          "system": "http://paciowg.github.io/cognitive-status-ig/CodeSystem/pacio-cat-cs",
          "code": "functioning",
          "display": "Functioning"
        }
      ]
    },
    {
      "coding": [
        {
          "system": "http://terminology.hl7.org/CodeSystem/observation-category",
          "code": "survey",
          "display": "Survey"
        }
      ]
    }
  ],
  "code": {
    "coding": [
      {
        "system": "http://loinc.org",
        "code": "85054-5",
        "display": "Self-care - discharge goal [CMS Assessment]"
      }
    ]
  },
  "subject": {
    "reference": "Patient/patientBSJ1"
  },
  "effectiveDateTime": "2020-07-11T16:32:00-05:00",
  "performer": [
    {
      "reference": "PractitionerRole/Role-OT-JenCadbury"
    }
  ],
  "hasMember": [
    {
      "reference": "Observation/FSC-SNF-DischargeGoal-Mobility-SelfCare-1-Ob-Question-29"
    },
    {
      "reference": "Observation/FSC-SNF-DischargeGoal-Mobility-SelfCare-1-Ob-Question-30"
    },
    {
      "reference": "Observation/FSC-SNF-DischargeGoal-Mobility-SelfCare-1-Ob-Question-31"
    },
    {
      "reference": "Observation/FSC-SNF-DischargeGoal-Mobility-SelfCare-1-Ob-Question-32"
    },
    {
      "reference": "Observation/FSC-SNF-DischargeGoal-Mobility-SelfCare-1-Ob-Question-33"
    },
    {
      "reference": "Observation/FSC-SNF-DischargeGoal-Mobility-SelfCare-1-Ob-Question-34"
    },
    {
      "reference": "Observation/FSC-SNF-DischargeGoal-Mobility-SelfCare-1-Ob-Question-35"
    }
  ],
  "derivedFrom": [
    {
      "reference": "QuestionnaireResponse/QResponse-SNF-DischargeGoal-Mobility-SelfCare-1",
      "display": "Questionnaire Response"
    }
  ]
}