{
  "resourceType": "Observation",
  "id": "BetsySmithMDSWalk10feet",
  "meta": {
    "profile": [
      "http://pacioproject.org//StructureDefinition/pacio-fs"
    ]
  },
  "subject": {
    "reference": "Betsy Smith"
  },
  "status": "final",
  "effectiveDateTime": "2020-03-24",
  "code": {
    "coding": [
      {
        "code": "83208-9",
        "system": "http://loinc.org"
      }
    ]
  },
  "performer": [
    {
      "reference": "CMS Provider"
    }
  ],
  "valueCodeableConcept": {
    "coding": [
      {
        "code": "LA11757-4",
        "system": "http://loinc.org"
      }
    ]
  }
}
